split_openfeature/__init__.py
split_openfeature/split_provider.py
split_openfeature-1.0.0.dist-info/licenses/LICENSE
split_openfeature_provider/__init__.py
split_openfeature_provider/split_client_wrapper.py
split_openfeature_provider/split_provider.py
split_openfeature-1.0.0.dist-info/METADATA
split_openfeature-1.0.0.dist-info/WHEEL
split_openfeature-1.0.0.dist-info/top_level.txt
split_openfeature-1.0.0.dist-info/RECORD
