Metadata-Version: 2.4
Name: split_openfeature
Version: 1.0.0
Summary: Deprecated Python Split Provider for OpenFeature. Please use split-openfeature-provider.
Author: Robert Grassian
Author-email: robert.grassian@split.io
License: Apache License 2.0
Classifier: Programming Language :: Python :: 3
Classifier: Topic :: Software Development :: Libraries
Requires-Python: >=3.5
License-File: LICENSE
Dynamic: author
Dynamic: author-email
Dynamic: classifier
Dynamic: description
Dynamic: description-content-type
Dynamic: license
Dynamic: license-file
Dynamic: requires-python
Dynamic: summary
